thienkieu/__init__.py
thienkieu/show.py
thienkieu-0.1.2.dist-info/WHEEL
thienkieu-0.1.2.dist-info/METADATA
thienkieu-0.1.2.dist-info/RECORD
